bma220/__init__.py
bma220/bma220.py
bma220/bma220_const.py
bma220/bma220_lowg_detection.py
bma220/bma220_orientation.py
bma220/bma220_slope.py
bma220/bma220_tap_sensing.py
circuitpython_bma220-0.5.0.dist-info/LICENSE
circuitpython_bma220-0.5.0.dist-info/METADATA
circuitpython_bma220-0.5.0.dist-info/WHEEL
circuitpython_bma220-0.5.0.dist-info/top_level.txt
circuitpython_bma220-0.5.0.dist-info/RECORD
