Metadata-Version: 2.1
Name: circuitpython-bma220
Version: 0.5.0
Summary: BMA220 Bosch Circuitpython Driver library
Author-email: JDM <jdm@mozmail.com>
License: MIT
Project-URL: Homepage, https://github.com/jposada202020/CircuitPython_BMA220
Keywords: sensor,blinka,circuitpython,micropython,bma220,acceleration,digital,bosch,sensor
Classifier: Intended Audience :: Developers
Classifier: Topic :: Software Development :: Libraries
Classifier: Topic :: Software Development :: Embedded Systems
Classifier: Topic :: System :: Hardware
Classifier: License :: OSI Approved :: MIT License
Classifier: Programming Language :: Python :: 3
License-File: LICENSE
Requires-Dist: Adafruit-Blinka
Requires-Dist: adafruit-circuitpython-busdevice
Requires-Dist: adafruit-circuitpython-register
Provides-Extra: optional
